sepp/__init__.py
sepp/commons.py
sepp/create_order_with_soloplan.py
sepp/exceptions.py
sepp/extract_info_from_pdf.py
sepp/llm_prompts.py
sepp/process_email.py
sepp/sepp_main.py
sepp/settings.py
sepp/scripts/__init__.py
sepp/scripts/download_stammdaten_on_server.py
sepp/scripts/geocoding.py
sepp/scripts/llm_response_hardcoded_cases.py
sepp/scripts/mailing_script.py
sepp/scripts/mock_soloplan.py
sepp/scripts/setup_ms_graph.py
sepp/scripts/tests/__init__.py
sepp/scripts/tests/test_geocoding.py
sepp/scripts/tests/test_llm_response_hardcoded_cases.py
sepp/scripts/tests/test_mailing_script.py
sepp/tests/__init__.py
sepp/tests/test_create_order_with_soloplan.py
sepp/tests/test_extract_info_from_pdf.py
sepp/tests/test_process_email.py
sepp/tests/test_sepp_main.py
sepp_tools-0.1.5.dist-info/METADATA
sepp_tools-0.1.5.dist-info/WHEEL
sepp_tools-0.1.5.dist-info/top_level.txt
sepp_tools-0.1.5.dist-info/RECORD
