Metadata-Version: 2.4
Name: sepp_tools
Version: 0.1.5
Summary: Pdf transport orders reading and automatic soloplan order creation
Author-email: Kolibrain <info@kolibrain.de>
Requires-Python: >=3.10
Requires-Dist: googlemaps
Requires-Dist: imaplib2
Requires-Dist: numpy
Requires-Dist: openai
Requires-Dist: openpyxl
Requires-Dist: pandas
Requires-Dist: pdf2image
Requires-Dist: pillow
Requires-Dist: pre-commit
Requires-Dist: pyMuPDF
Requires-Dist: PyPDF2
Requires-Dist: pytest
Requires-Dist: python-dotenv
Requires-Dist: python-Levenshtein
Requires-Dist: requests
Requires-Dist: requests-toolbelt
Requires-Dist: transformers
Requires-Dist: urllib3
Requires-Dist: beautifulsoup4
Requires-Dist: datetime
Requires-Dist: django-environ
Requires-Dist: exchangelib
Requires-Dist: fpdf
Requires-Dist: geopy
